setup.py
ostat/__init__.py
ostat/ostat.py
ostat.egg-info/PKG-INFO
ostat.egg-info/SOURCES.txt
ostat.egg-info/dependency_links.txt
ostat.egg-info/not-zip-safe
ostat.egg-info/top_level.txt