Metadata-Version: 1.0
Name: ostat
Version: 0.0
Summary: efficient, accurate, and stable calculation of online statistical quantities.
Home-page: http://github.com/smcquay/ostat/
Author: Stephen McQuay
Author-email: stephen@mcquay.me
License: MIT
Platform: UNKNOWN
